abstergo_censor/__init__.py
abstergo_censor-0.1.3.dist-info/METADATA
abstergo_censor-0.1.3.dist-info/WHEEL
abstergo_censor-0.1.3.dist-info/entry_points.txt
abstergo_censor-0.1.3.dist-info/licenses/LICENSE
abstergo_censor-0.1.3.dist-info/RECORD
