Metadata-Version: 2.4
Name: abstergo-censor
Version: 0.1.3
Summary: Privacy-first CLI to blur faces and license plates (OpenCV Haar cascades)
Author: Abstergo LLC
License: MIT
License-File: LICENSE
Requires-Python: >=3.9
Requires-Dist: opencv-python>=4.9.0.80
